multy/__init__.py
multy/bulk_query.py
multy-1.0.1.dist-info/LICENSE
multy-1.0.1.dist-info/METADATA
multy-1.0.1.dist-info/WHEEL
multy-1.0.1.dist-info/top_level.txt
multy-1.0.1.dist-info/RECORD
