Metadata-Version: 2.1
Name: multy
Version: 1.0.1
Summary: Easily implement bulk insert and ON DUPLICATE KEY UPDATEstatements with MySQL and MariaDB
Home-page: https://github.com/hashimura-suguru/multy_py
Author: hashimura suguru
Author-email: sugurudesu515@gmail.com
License: MIT
Keywords: MariaDB,MySQL,Bulk,Multiple,Query
Platform: UNKNOWN
Classifier: Development Status :: 4 - Beta
Classifier: Programming Language :: Python :: 3
Classifier: Programming Language :: Python :: 3.4
Classifier: Programming Language :: Python :: 3.5
Classifier: Programming Language :: Python :: 3.6
Classifier: Programming Language :: Python :: 3.7
Classifier: Programming Language :: Python :: 3.8
Classifier: Intended Audience :: Developers
Classifier: License :: OSI Approved :: MIT License
